pmakefile/__init__.py
pmakefile-0.4.5.dist-info/entry_points.txt
pmakefile-0.4.5.dist-info/LICENSE
pmakefile-0.4.5.dist-info/METADATA
pmakefile-0.4.5.dist-info/WHEEL
pmakefile-0.4.5.dist-info/RECORD
