Metadata-Version: 2.1
Name: pmakefile
Version: 0.4.5
Summary: 
Author: thautwarm
Author-email: twshere@outlook.com
Requires-Python: >=3.7,<4.0
Classifier: Programming Language :: Python :: 3
Classifier: Programming Language :: Python :: 3.7
Classifier: Programming Language :: Python :: 3.8
Classifier: Programming Language :: Python :: 3.9
Classifier: Programming Language :: Python :: 3.10
Classifier: Programming Language :: Python :: 3.11
Classifier: Programming Language :: Python :: 3.12
Requires-Dist: wisepy2 (>=1.4.1,<2.0.0)
